Workbook

Sheet Identification Form
A1: Small Scale Project Identification Form Identifikační formulář malého lokálního projektu
A2: HOW TO FILL IN THIS FORM | Please fill in only the white cells. Shaded cells are calculated automatically or reserved for the Embassy and are locked. Do not delete rows or columns. Amounts are entered in local currency or EUR/USD; the Czech koruna (CZK) equivalent is calculated from the exchange rate set by the Embassy. The budget is divided into project costs (block A), which directly create the outputs of the project, and support costs (block B), which do not create an output but are necessary for the preparation, management or administration of the project. Support costs must not exceed 8 % of the total of the support from the Czech development cooperation funding**. Text fields have character limits shown on the right of each field; be concise and specific. Only this sheet is filled in when a project proposal is submitted. The Final Report and Financial Report sheets are completed after an approved project has been implemented — leave them empty when submitting a proposal. JAK FORMULÁŘ VYPLNIT | Bílé buňky vyplňuje žadatel. Šedé buňky se počítají automaticky nebo jsou vyhrazeny velvyslanectví a jsou zamčené. Nemažte řádky ani sloupce. Částky se zadávají v místní měně nebo v EUR/USD; ekvivalent v českých korunách (Kč) se počítá z kurzu stanoveného velvyslanectvím. Rozpočet se dělí na projektové náklady (blok A), které přímo vytvářejí výstupy projektu, a podpůrné náklady (blok B), které výstup nevytvářejí, ale jsou nutné pro přípravu, řízení nebo administraci projektu. Podpůrné náklady nesmí přesáhnout 8 % celkové částky z finanční podpory České republiky. U textových polí je vpravo uveden limit počtu znaků; pište stručně a konkrétně. Při podání námětu se vyplňuje pouze tento list. Listy Závěrečná zpráva (Final Report) a Finanční zpráva (Financial Report) se vyplňují až po realizaci schváleného projektu — při podání námětu je ponechte prázdné.
A3: Project Title (short yet clear) Název projektu (stručně) | C3: Safe Waters – Youth Water Rescue Training and Response Unit | G3: Project Number (assigned by Embassy) Číslo projektu (přiděluje velvyslanectví)
A4: Country Země | C4: Bosnia and Herzegovina | G4: Project Location (village / district — be specific) Místo realizace (obec / okres — buďte konkrétní) | I4: Sarajevo (club headquarters); Jablaničko Lake (rescue boat base) and Boračko Lake, Konjic Municipality, Herzegovina-Neretva Canton
A5: Beginning of Project (month / year) Zahájení projektu (měsíc / rok) | C5: April 2027 | G5: Termination of Project (month / year) Ukončení projektu (měsíc / rok) | I5: October 2027
A6: 1. Requested Funding from the Czech Republic Official Development Assistance (calculated automatically from section 10) 1. Požadovaná částka ze zahraniční rozvojové spolupráce České republiky (počítá se automaticky z bodu 10)
A7: In Local Currency V místní měně | G7: =H157 -> 36970
A8: In CZK (according to Czech Embassy Exchange Rate) V Kč (podle kurzu stanoveného velvyslanectvím ČR) | G8: =I157 -> 461974.86
A9: In CZK including exchange rate reserve — amount to be stated in the contract V Kč včetně kurzové rezervy — částka, která se uvede ve smlouvě | G9: =I173 -> 475834.1
A10: 2. Additional Funding from Other Sources (if applicable) (calculated automatically from section 10) 2. Další zdroje financování (pokud existují) (počítá se automaticky z bodu 10)
A11: In Local Currency V místní měně | G11: =H168 -> 5000
A12: In CZK (according to Czech Embassy Exchange Rate) V Kč (podle kurzu stanoveného velvyslanectvím ČR) | G12: =IF($I$93=0,"",H168/$I$93) -> 62479.694
A13: 3. Total Project Budget 3. Celkový rozpočet projektu
A14: In Local Currency V místní měně | G14: =H157+H168 -> 41970
A15: In CZK (according to Czech Embassy Exchange Rate) V Kč (podle kurzu stanoveného velvyslanectvím ČR) | G15: =IF($I$93=0,"",(H157+H168)/$I$93) -> 524454.55
A16: Share of co-financing in the total project budget Podíl spolufinancování na celkovém rozpočtu projektu | G16: =IF((H157+H168)=0,"",H168/(H157+H168)) -> 0.11913271
A17: 4. Applicant 4. Žadatel
A18: Name of Organization Název organizace | E18: Klub vodenih sportova „S.C.U.B.A.“ Sarajevo (KVS SCUBA)
A19: Telephone Number Telefonní číslo | E19: +387 62 332 082
A20: Email Address E-mailová adresa | E20: kvsscuba@gmail.com
A21: Website Webové stránky | E21: www.scubasarajevo.com
A22: Document proving legal personality attached Přiložen doklad o právní subjektivitě | E22: Yes / Ano | H22: Non-state applicants must attach the aforementioned documents along with this form. Nestátní žadatelé musí spolu s tímto formulářem přiložit výše uvedené doklady.
A23: Document proving authority to act attached Přiložen doklad o oprávnění jednat za organizaci | E23: Yes / Ano
A24: 5. Local Priority Targeted by the Project and Target Group 5. Místní priorita a cílová skupina
A25: 5.1 Target group 5.1 Cílová skupina
A26: Be as specific as possible. Direct beneficiaries are people who use the project outputs themselves. Uveďte co nejkonkrétnější údaje. Přímí příjemci jsou lidé, kteří sami využívají výstupy projektu.
A27: Beneficiaries Příjemci | E27: Number of persons Počet osob | G27: Who they are (age, gender, role — e.g. 120 pupils aged 6–14, 8 teachers) O koho jde (věk, pohlaví, role — např. 120 žáků ve věku 6–14 let, 8 učitelů)
A28: Direct beneficiaries Přímí příjemci | E28: 15 | G28: 15 young divers aged 16–25, members of KVS SCUBA (priority access for socially vulnerable youth), trained and certified as water-rescue divers; 4 senior members (two diving pairs) additionally equipped with dry suits as duty leads
A29: Indirect beneficiaries Nepřímí příjemci | E29: 5000 | G29: Estimated visitors, tourists and local residents at Jablaničko Lake and Boračko Lake (Konjic Municipality) during the 2027 summer season, who benefit from a volunteer water-rescue presence and public safety outreach (estimate)
A30: 5.2 Local priority addressed by the project 5.2 Místní priorita adresovaná projektem
A31: Describe the local priority as it affects the target group identified in 5.1. Use data for the specific location of the intervention. Popište místní prioritu tak, jak se dotýká cílové skupiny uvedené v bodě 5.1. Použijte údaje o konkrétním místě realizace.
A32: Jablaničko Lake and Boračko Lake, near Konjic, are popular inland recreation sites for swimmers, divers, campers and tourists in summer. To the Club's knowledge, neither lake has a permanent lifeguard or organised water-rescue service. The floods of October 2024, which killed at least 25 people in Bosnia and Herzegovina, the large majority in the Jablanica and Konjic area, showed how limited local water-rescue capacity is. KVS SCUBA regularly organises open-water training on both lakes and its divers are often the nearest people with relevant skills when incidents occur, but the Club has no formal rescue training, rescue boat or lifesaving equipment to respond safely and effectively. Visitors and families therefore use these lakes without organised safety coverage. | L32: =LEN(A32)&" / 1000" -> 775 / 1000
A33: 5.3 Identification 5.3 Identifikace
A34: State how the local priority was identified. Select the closest option and explain briefly who requested the project, when, and on what basis. Uveďte, jak byla místní priorita identifikována. Vyberte nejbližší možnost a stručně vysvětlete, kdo o projekt požádal, kdy a na jakém základě.
A35: How was the local priority identified? Jak byla místní priorita identifikována? | E35: Local priority assessment / analýza místních priorit | G35: Identified by KVS SCUBA through its own experience organising diving activities and open-water training on Jablaničko and Boračko Lake, and reinforced by the October 2024 floods in the same area, which highlighted the lack of organised local water-rescue capacity.
A36: 5.4 Proposed solution 5.4 Navrhované řešení
A37: Describe the proposed solution and explain why this solution rather than another. State what will change for the target group. Popište navrhované řešení a vysvětlete, proč právě toto řešení, a ne jiné. Uveďte, co se pro cílovou skupinu změní.
A38: KVS SCUBA will establish a volunteer Water Rescue Unit. A core team of club divers will complete the SSI React Right (first aid, CPR, AED, oxygen) and Diver Stress & Rescue courses and will be equipped with a new zero-emission electric-powered inflatable boat for 4–6 divers, four dry suits (two diving pairs), an AED, oxygen first-aid and rescue equipment. In summer 2027 the unit will provide scheduled volunteer safety presence at Jablaničko Lake and Boračko Lake, plus a water-safety awareness campaign for local schools and communities. This replaces today's ad-hoc help by individual divers with an organised, equipped and repeatable rescue capacity. The unit will also make its capacities available to the local Civil Protection service in emergencies. | L38: =LEN(A38)&" / 800" -> 759 / 800
A39: 6. Linkage to Other Activities 6. Návaznost na další aktivity
A40: Mark Yes or No for every line. If Yes, specify in the right-hand column. If the project has no linkage, mark No — this is not a disqualifying answer. U každého řádku označte Ano, nebo Ne. Pokud ano, upřesněte v pravém sloupci. Pokud projekt na nic nenavazuje, označte Ne — tato odpověď není důvodem k vyřazení.
A41: 6.1 Type of linkage 6.1 Typ návaznosti
A42: Area of linkage Oblast návaznosti | G42: Yes / No Ano / Ne | H42: If Yes, specify Pokud ano, upřesněte
A43: Czech development or humanitarian activities in the country (state the project or programme) České rozvojové nebo humanitární aktivity v zemi (uveďte projekt nebo program) | G43: No / Ne
A44: Previous Small Scale Project supported by this Embassy (state year and title) Předchozí malý lokální projekt podpořený tímto velvyslanectvím (uveďte rok a název) | G44: No / Ne
A45: Activities of other donors or a programme of the partner country Aktivity jiných dárců nebo program partnerské země | G45: Yes / Ano | H45: Club applied in 2026 to JP BH POŠTA d.o.o. Sarajevo for support of its youth diver training programme “Ronioci sutrašnjice” (decision pending). No overlap with this project: that programme funds training and certification of young divers, not rescue boat or rescue equipment.
A46: Czech economic presence, Czech suppliers or Czech technology Česká ekonomická přítomnost, čeští dodavatelé nebo české technologie | G46: No / Ne
A47: Czech compatriot community or teaching of the Czech language Česká krajanská komunita nebo výuka českého jazyka | G47: No / Ne
A48: Follow-up planned by the applicant after this project ends Navazující aktivity plánované žadatelem po skončení tohoto projektu | G48: Yes / Ano | H48: Permanent continuation of the volunteer water-rescue unit, operating every summer season from 2027 onward, funded through club membership fees and local sponsorship
A49: Other comments or notes on linkages (optional) Další poznámky k návaznostem (nepovinné) | H49: The Club welcomes the opportunity to establish cooperation with Czech water-rescue or diving organisations (e.g. the Czech Red Cross Water Rescue Service) to exchange know-how during project implementation. The unit's availability to local Civil Protection is part of the project (see Activities)
A50: 6.2 Relation to a Previously Supported Small Scale Project 6.2 Vztah k dříve podpořenému malému lokálnímu projektu
A51: Does this proposal coincide with a previously supported Small Scale Project in its subject, its implementer and its place of implementation at the same time? Shoduje se tento námět s dříve podpořeným malým lokálním projektem zároveň v předmětu, v realizátorovi i v místě realizace? | J51: No / Ne
A52: If Yes, state whether the project extends or scales up the original intervention, replicates it for another target group, or constitutes a follow-up phase with different outputs. Pokud ano, uveďte, zda projekt původní intervenci rozšiřuje, opakuje ji pro jinou cílovou skupinu, nebo jde o navazující fázi s jinými výstupy.
A53: N/A — new initiative, not a continuation of a specific previously supported project. | L53: =LEN(A53)&" / 600" -> 84 / 600
A54: 7. Project Activities, Outputs and Indicators 7. Aktivity, výstupy a indikátory projektu
A55: List activities as numbered items. Every activity must produce an output that can be verified. An indicator is a number the Embassy can verify at the end of the project on site, by video call, from photographs or from documentation. Aktivity uveďte jako číslované položky. Každá aktivita musí mít ověřitelný výstup. Indikátor je číslo, které velvyslanectví může na konci projektu ověřit na místě, videohovorem, z fotografií nebo z dokumentace.
A56: No. Č. | B56: Activity Aktivita | D56: Output (what will be created) Výstup (co vznikne) | F56: Indicator Indikátor | H56: Target value Cílová hodnota | I56: Means of verification Způsob ověření | K56: Month of implementation Měsíc realizace
A57: e.g. / např. | B57: Delivery and installation of two 3D printers for the school workshop / Dodávka a instalace dvou 3D tiskáren do školní dílny | D57: Two 3D printers installed and put into operation / Dvě 3D tiskárny instalované a uvedené do provozu | F57: Number of 3D printers installed and handed over / Počet instalovaných a předaných 3D tiskáren | H57: 2 | I57: Handover protocol, invoice, photographs / Předávací protokol, faktura, fotografie | K57: Months 2–3 / 2.–3. měsíc
A58: EXAMPLE ROW ABOVE / VÝŠE UVEDENÝ ŘÁDEK JE PŘÍKLAD
A59: 1 | B59: Procurement of new electric-powered inflatable boat, electric outboard motor, registration and insurance | D59: Zero-emission rescue/dive boat operational and registered | F59: Number of boats procured and registered | H59: 1 | I59: Purchase invoice, registration documents, photographs | K59: Months 1–2
A60: 2 | B60: Procurement of dry suits with undergarments, rescue set (buoys, line, oxygen kit), AED and VHF radios | D60: Core rescue equipment available and in use | F60: Number of dry suits / rescue sets / AEDs / radios procured | H60: 4 / 1 / 1 / 2 | I60: Invoices, equipment inventory list, photographs | K60: Months 1–2
A61: 3 | B61: Adaptation of existing space for secure equipment storage and maintenance; servicing of club compressor, cylinders and regulators (Club-funded) | D61: Storage space and training equipment ready for use | F61: Storage adapted and equipment serviced (yes/no) | H61: 1 | I61: Photographs, service records | K61: Months 1–2
A62: 4 | B62: SSI Diver Stress & Rescue course for the same 15 participants | D62: Certified rescue divers | F62: Number of participants certified | H62: 15 | I62: Certification cards, course attendance list | K62: Months 3–4
A63: 5 | B63: SSI React Right course (first aid, CPR, AED, oxygen) for 15 club divers | D63: First-aid certified volunteers | F63: Number of participants certified | H63: 15 | I63: Certificates, attendance list | K63: Months 2–3
A64: 6 | B64: Volunteer duty roster at Jablaničko Lake and Boračko Lake (boat and divers) | D64: Water-rescue unit present on site | F64: Number of duty days covered | H64: 30 | I64: Duty logbook, photographs | K64: Months 3–6
A65: 7 | B65: Water-safety awareness sessions for local schools and communities | D65: Awareness sessions held, materials distributed | F65: Number of people reached | H65: 500 | I65: Attendance sheets, photographs, materials | K65: Months 3–6
A66: 8 | B66: Public handover and launch event with the Embassy | D66: Public event held | F66: Event held (yes/no) | H66: 1 | I66: Photographs, media coverage, guest list | K66: Month 3
A67: 9 | B67: Agreement with the local Civil Protection service on availability of the unit's boat, divers and equipment in emergencies | D67: Cooperation arrangement with Civil Protection in place | F67: Written agreement or protocol signed (yes/no) | H67: 1 | I67: Signed agreement/protocol or confirmation letter | K67: Months 3–4
A68: 10
A69: 8. Sustainability and Ownership of the Outputs 8. Udržitelnost a vlastnictví výstupů
A70: Sections 8.1 to 8.6 concern the situation after the project has ended and the Czech funding has stopped. Fill in relevant/applicable cells. Body 8.1 až 8.6 se týkají situace po skončení projektu a po ukončení českého financování. Vyplňte relevantní buňky.
A71: 8.1 Who will own the outputs after the project ends? (name of the entity) 8.1 Kdo bude výstupy po skončení projektu vlastnit? (název subjektu) | G71: KVS SCUBA (registered diving association, Sarajevo)
A72: 8.2 Who will operate and maintain the outputs? (name of the entity / responsible person) 8.2 Kdo bude výstupy provozovat a udržovat? (název subjektu / odpovědná osoba) | G72: KVS SCUBA technical team and Water Rescue Unit duty leads
A73: 8.3 Estimated annual running and maintenance costs 8.3 Odhadované roční provozní a udržovací náklady | G73: 3000 | I73: Covered from (source) Hrazeno z (zdroj) | J73: Club membership fees and local sponsorship
A74: 8.4 Describe how the benefits for the target group will continue after the project ends. 8.4 Popište, jak budou přínosy pro cílovou skupinu pokračovat po skončení projektu.
A75: The boat, dry suits, AED and rescue equipment remain the property of KVS SCUBA and will be used every season from 2027 onward. The trained, certified volunteer divers continue as active club members, renewing their skills through the club's regular training programme. The duty roster at Jablaničko Lake and Boračko Lake will be repeated each summer season, funded through membership fees, local sponsorship and, where available, municipal or tourism-board support, ensuring the water-rescue presence continues after Czech funding ends. | L75: =LEN(A75)&" / 800" -> 536 / 800
A76: 8.5 Describe how the target group (and the partner institution if applicable) were involved in the identification of the local priority, in the design of the project and in its implementation, and how they will take part in the operation of the outputs. 8.5 Popište, jak byly cílová skupina (a partnerská instituce pokud je zapojena) zapojena do identifikace místní priority, do přípravy projektu a do jeho realizace a jak se budou podílet na provozu výstupů.
A77: The target group - KVS SCUBA's own young divers - identified the need for rescue training through their direct experience organising dives and events at Jablaničko Lake and Boračko Lake. Club members and instructors defined the training programme and equipment list together with the Club's governing board. Trainees participate in every stage: equipment testing and fitting, the certification courses themselves, and subsequently as volunteer duty-roster members operating and maintaining the boat and equipment throughout the project and beyond. | L77: =LEN(A77)&" / 800" -> 547 / 800
A78: 8.6 State the main risks to the implementation of the project and how they will be addressed. 8.6 Uveďte hlavní rizika realizace projektu a způsob, jakým budou řešena.
A79: Key risks: (1) boat/equipment damage or theft – secure storage and insurance; (2) volunteer availability – rotating roster of 15 trained divers; (3) permits and operator licences for the boat and VHF radios – obtained before procurement is completed; (4) price increases – 3% exchange-rate reserve and cautious budget; (5) limited speed and range of electric propulsion – spare charging plan, coordination with Civil Protection for fast response; (6) weather limiting duty days – flexible scheduling. | L79: =LEN(A79)&" / 600" -> 500 / 600
A80: 9. Visibility of Czech Assistance 9. Viditelnost české pomoci
A81: The material outputs of the project must be marked with the logo of the Ministry of Foreign Affairs of the Czech Republic (MFA CZ logo) or the CzechAid logo, both provided by Embassy upon request; for intangible outputs the support from the Czech Republic must always be stated, both when the outputs are presented and in the materials arising from them. The applicant is required to provide photographs of the marked outputs with the final report. Hmotné výstupy projektu musí být označeny logem Ministerstva zahraničních věcí České republiky (logo MZV ČR) nebo logem CzechAid; obě loga poskytne velvyslanectví na vyžádání. U nehmotných výstupů musí být podpora České republiky vždy uvedena, a to jak při jejich prezentaci, tak v materiálech, které z nich vycházejí. Žadatel je povinen předložit se závěrečnou zprávou fotografie označených výstupů.
A82: 9.1 How will the outputs be marked with the MFA CZ logo/CzechAid logo? (plaque, sticker on equipment, banner, printed materials) 9.1 Jak budou výstupy označeny logem MZV ČR / CzechAid? (pamětní deska, samolepka na vybavení, banner, tištěné materiály) | G82: Czech Development Cooperation logo (per Embassy visibility rules) on the rescue boat, an information plaque at the equipment storage site, dry suits and equipment bags, banners at training sessions and the handover event, and all printed materials with an acknowledgement text.
A83: 9.2 Who will become aware of the Czech assistance through this project? 9.2 Kdo se o české pomoci prostřednictvím tohoto projektu dozví?
A84: Audience Publikum | G84: Estimated number of people Odhadovaný počet osob | I84: Note (name of the community, institution, medium) Poznámka (název komunity, instituce, média)
A85: Local community where the project takes place Místní komunita v místě realizace projektu | G85: 5000 | I85: Visitors and residents at Jablaničko Lake / Boračko Lake, Konjic Municipality
A86: Staff and users of the partner institution Zaměstnanci a uživatelé partnerské instituce
A87: Local or regional media Místní nebo regionální média | G87: 3000 | I87: Expected reach via local Sarajevo/Konjic media outlets and the Club's social media channels (estimate)
A88: Participants of a public event (handover, opening) Účastníci veřejné akce (předání, slavnostní otevření) | G88: 80 | I88: Local community members, club members, local authorities and media invited to the season-opening/handover event
A89: 9.3 Handover or opening event with the participation of the Embassy is planned 9.3 Je plánováno předání nebo slavnostní otevření za účasti velvyslanectví | I89: Yes / Ano | J89: Expected month Předpokládaný měsíc | K89: June 2027
A90: 9.4 The applicant undertakes to provide at least this number of photographs of the marked outputs with the final report 9.4 Žadatel se zavazuje předložit se závěrečnou zprávou alespoň tento počet fotografií označených výstupů | K90: 20
A91: The photographs must not allow individual persons to be identified unless the applicant holds a valid legal basis for taking the photographs, handing them over to the Embassy and their use for the presentation of Czech development cooperation. Fotografie nesmí umožnit identifikaci jednotlivých osob, ledaže žadatel má platný právní titul k jejich pořízení, k jejich předání velvyslanectví a k jejich užití pro prezentaci české rozvojové spolupráce.
A92: 10. Budget Proposal*** 10. Návrh rozpočtu
A93: Currency used (code) Použitá měna (kód) | C93: BAM | E93: Exchange rate: units of local currency per 1 CZK (set by the Embassy) Kurz: jednotek místní měny za 1 Kč (stanoví velvyslanectví) | I93: 0.080026 | J93: Date of rate Datum kurzu | K93: 12.10.2026
A94: Enter amounts in local currency only. The CZK column is calculated from the exchange rate above. Block A covers costs that directly create an output of the project. Block B covers costs that do not create an output but are necessary for the preparation, management or administration of the project; the total of block B must not exceed 8 % of the grand total. Overhead costs of the implementing organization cannot be paid from the project budget. Částky uvádějte pouze v místní měně. Sloupec v Kč se počítá z výše uvedeného kurzu. Blok A zahrnuje náklady, které přímo vytvářejí výstup projektu. Blok B zahrnuje náklady, které výstup nevytvářejí, ale jsou nutné pro přípravu, řízení nebo administraci projektu; součet bloku B nesmí přesáhnout 8 % celkové částky. Režijní náklady realizující organizace nelze z rozpočtu projektu hradit.
A95: No. Č. | B95: Type of Costs Druh nákladů | E95: Unit Jednotka | F95: Number of Units Počet jednotek | G95: Unit Price Cena za jednotku | H95: Total (local) Celkem (místní měna) | I95: Total (CZK) Celkem (Kč) | J95: % of total % z celku | K95: Note (optional) Poznámka (nepovinné)
A96: A. PROJECT COSTS — costs that directly create an output of the project A. PROJEKTOVÉ NÁKLADY — náklady, které přímo vytvářejí výstup projektu
A97: A.1 Material, Goods and Equipment, including their transport and installation A.1 Materiál, zboží a vybavení včetně jejich dopravy a instalace
A98: 1 | B98: New inflatable boat with aluminium floor (approx. 3.5 m, capacity 4–6 divers) | E98: pcs | F98: 1 | G98: 6500 | H98: =IF(OR(F98="",G98=""),"",F98*G98) -> 6500 | I98: =IF(H98="","",IF($I$93=0,"",H98/$I$93)) -> 81223.602 | J98: =IF(H98="","",IF($H$157=0,"",H98/$H$157)) -> 0.17581823
A99: 2 | B99: Electric outboard motor (approx. 3 hp equivalent, integrated lithium battery) – zero-emission propulsion | E99: pcs | F99: 1 | G99: 4500 | H99: =IF(OR(F99="",G99=""),"",F99*G99) -> 4500 | I99: =IF(H99="","",IF($I$93=0,"",H99/$I$93)) -> 56231.725 | J99: =IF(H99="","",IF($H$157=0,"",H99/$H$157)) -> 0.12172031
A100: 3 | B100: Boat registration, technical inspection and first-year insurance policy | E100: lump sum | F100: 1 | G100: 800 | H100: =IF(OR(F100="",G100=""),"",F100*G100) -> 800 | I100: =IF(H100="","",IF($I$93=0,"",H100/$I$93)) -> 9996.7511 | J100: =IF(H100="","",IF($H$157=0,"",H100/$H$157)) -> 0.021639167
...

Sheet Financial Report
A1: Financial Report on Small Scale Project Implementation Finanční zpráva o realizaci malého lokálního projektu
A2: THIS SHEET IS COMPLETED ONLY FOR AN APPROVED PROJECT, AFTER THE IMPLEMENTATION HAS ENDED, including early termination. Grey cells are taken from the Identification Form or are calculated; fill in the white cells only. For every budget line enter the amount actually spent in the currency of implementation AND the corresponding amount in CZK - for that purpose the Embassy will provide used exchange rate for each payment. The CZK amounts are NOT derived from an exchange rate — enter the CZK amount that was actually converted or actually drawn from the Czech funds, so that payments made at different exchange rates on different dates are reported correctly. If one line was paid at more than one rate, enter the sum of the amounts actually paid in each currency. The Financial Report must be SIGNED by the authorised person of the implementer before submission (signature block at the end of this sheet). TENTO LIST SE VYPLŇUJE POUZE U SCHVÁLENÉHO PROJEKTU, A TO AŽ PO UKONČENÍ REALIZACE, včetně předčasného ukončení. Šedé buňky se přebírají z identifikačního formuláře nebo se počítají; vyplňujte pouze bílé buňky. U každé rozpočtové položky uveďte skutečně vynaloženou částku v měně realizace a odpovídající částku v Kč, velvyslanectví poskytne použitý kurz pro přepočet na Kč k jednotlivým platbám. Částky v Kč se nepočítají z kurzu — uveďte částku v Kč, která byla skutečně směněna nebo skutečně čerpána z českých prostředků, aby bylo možné správně vykázat platby provedené v různých dnech a různými kurzy. Pokud byla jedna položka hrazena více kurzy, uveďte součet částek skutečně zaplacených v každé měně. Finanční zpráva musí být před odesláním PODEPSÁNA oprávněnou osobou realizátora (podpisový blok na konci tohoto listu).
A3: No. Č. | B3: Type of Costs (from Identification Form) Druh nákladů (z identifikačního formuláře) | D3: Approved Units Schválený počet jednotek | E3: Approved Unit Price Schválená cena za jednotku | F3: Approved Total (local currency) Schválená částka celkem (místní měna) | G3: Real Units Skutečný počet jednotek | H3: Real Total (local currency) Skutečně celkem (místní měna) | I3: Real Total (CZK) Skutečně celkem (Kč) | J3: Approved Total (CZK) Schválená částka celkem (Kč) | K3: Difference (CZK) Rozdíl (Kč) | L3: Check Kontrola
A4: A. PROJECT COSTS A. PROJEKTOVÉ NÁKLADY
A5: A.1 Material, Goods and Equipment, including their transport and installation A.1 Materiál, zboží a vybavení včetně jejich dopravy a instalace
A6: 1 | B6: =IF('Identification Form'!B98="","",'Identification Form'!B98) -> New inflatable boat with aluminium floor (approx. 3.5 m, capacity 4–6 divers) | D6: =IF('Identification Form'!F98="","",'Identification Form'!F98) -> 1 | E6: =IF('Identification Form'!G98="","",'Identification Form'!G98) -> 6500 | F6: =IF('Identification Form'!H98="","",'Identification Form'!H98) -> 6500 | J6: =IF('Identification Form'!I98="","",'Identification Form'!I98) -> 81223.602 | K6: =IF(OR(J6="",I6=""),"",I6-J6) | L6: =IF(AND(H6="",I6=""),"",IF(H6="","local amount missing / chybí částka v místní měně",IF(I6="","CZK amount missing / chybí částka v Kč","")))
A7: 2 | B7: =IF('Identification Form'!B99="","",'Identification Form'!B99) -> Electric outboard motor (approx. 3 hp equivalent, integrated lithium battery) – zero-emission propulsion | D7: =IF('Identification Form'!F99="","",'Identification Form'!F99) -> 1 | E7: =IF('Identification Form'!G99="","",'Identification Form'!G99) -> 4500 | F7: =IF('Identification Form'!H99="","",'Identification Form'!H99) -> 4500 | J7: =IF('Identification Form'!I99="","",'Identification Form'!I99) -> 56231.725 | K7: =IF(OR(J7="",I7=""),"",I7-J7) | L7: =IF(AND(H7="",I7=""),"",IF(H7="","local amount missing / chybí částka v místní měně",IF(I7="","CZK amount missing / chybí částka v Kč","")))
A8: 3 | B8: =IF('Identification Form'!B100="","",'Identification Form'!B100) -> Boat registration, technical inspection and first-year insurance policy | D8: =IF('Identification Form'!F100="","",'Identification Form'!F100) -> 1 | E8: =IF('Identification Form'!G100="","",'Identification Form'!G100) -> 800 | F8: =IF('Identification Form'!H100="","",'Identification Form'!H100) -> 800 | J8: =IF('Identification Form'!I100="","",'Identification Form'!I100) -> 9996.7511 | K8: =IF(OR(J8="",I8=""),"",I8-J8) | L8: =IF(AND(H8="",I8=""),"",IF(H8="","local amount missing / chybí částka v místní měně",IF(I8="","CZK amount missing / chybí částka v Kč","")))
A9: 4 | B9: =IF('Identification Form'!B101="","",'Identification Form'!B101) -> Professional neoprene dry suits for rescue divers (two diving pairs) | D9: =IF('Identification Form'!F101="","",'Identification Form'!F101) -> 4 | E9: =IF('Identification Form'!G101="","",'Identification Form'!G101) -> 2700 | F9: =IF('Identification Form'!H101="","",'Identification Form'!H101) -> 10800 | J9: =IF('Identification Form'!I101="","",'Identification Form'!I101) -> 134956.14 | K9: =IF(OR(J9="",I9=""),"",I9-J9) | L9: =IF(AND(H9="",I9=""),"",IF(H9="","local amount missing / chybí částka v místní měně",IF(I9="","CZK amount missing / chybí částka v Kč","")))
A10: 5 | B10: =IF('Identification Form'!B102="","",'Identification Form'!B102) -> Thermal undergarments for dry suits | D10: =IF('Identification Form'!F102="","",'Identification Form'!F102) -> 4 | E10: =IF('Identification Form'!G102="","",'Identification Form'!G102) -> 450 | F10: =IF('Identification Form'!H102="","",'Identification Form'!H102) -> 1800 | J10: =IF('Identification Form'!I102="","",'Identification Form'!I102) -> 22492.69 | K10: =IF(OR(J10="",I10=""),"",I10-J10) | L10: =IF(AND(H10="",I10=""),"",IF(H10="","local amount missing / chybí částka v místní měně",IF(I10="","CZK amount missing / chybí částka v Kč","")))
A11: 6 | B11: =IF('Identification Form'!B103="","",'Identification Form'!B103) -> Water-rescue set: rescue buoys, floating rescue line, first-aid kit with oxygen | D11: =IF('Identification Form'!F103="","",'Identification Form'!F103) -> 1 | E11: =IF('Identification Form'!G103="","",'Identification Form'!G103) -> 2000 | F11: =IF('Identification Form'!H103="","",'Identification Form'!H103) -> 2000 | J11: =IF('Identification Form'!I103="","",'Identification Form'!I103) -> 24991.878 | K11: =IF(OR(J11="",I11=""),"",I11-J11) | L11: =IF(AND(H11="",I11=""),"",IF(H11="","local amount missing / chybí částka v místní měně",IF(I11="","CZK amount missing / chybí částka v Kč","")))
A12: 7 | B12: =IF('Identification Form'!B104="","",'Identification Form'!B104) -> Automated external defibrillator (AED) with carry case and spare pads | D12: =IF('Identification Form'!F104="","",'Identification Form'!F104) -> 1 | E12: =IF('Identification Form'!G104="","",'Identification Form'!G104) -> 2500 | F12: =IF('Identification Form'!H104="","",'Identification Form'!H104) -> 2500 | J12: =IF('Identification Form'!I104="","",'Identification Form'!I104) -> 31239.847 | K12: =IF(OR(J12="",I12=""),"",I12-J12) | L12: =IF(AND(H12="",I12=""),"",IF(H12="","local amount missing / chybí částka v místní měně",IF(I12="","CZK amount missing / chybí částka v Kč","")))
A13: 8 | B13: =IF('Identification Form'!B105="","",'Identification Form'!B105) -> Handheld waterproof VHF marine radios (the Club already owns 4 units) | D13: =IF('Identification Form'!F105="","",'Identification Form'!F105) -> 2 | E13: =IF('Identification Form'!G105="","",'Identification Form'!G105) -> 250 | F13: =IF('Identification Form'!H105="","",'Identification Form'!H105) -> 500 | J13: =IF('Identification Form'!I105="","",'Identification Form'!I105) -> 6247.9694 | K13: =IF(OR(J13="",I13=""),"",I13-J13) | L13: =IF(AND(H13="",I13=""),"",IF(H13="","local amount missing / chybí částka v místní měně",IF(I13="","CZK amount missing / chybí částka v Kč","")))
A14: 9 | B14: =IF('Identification Form'!B106="","",'Identification Form'!B106) | D14: =IF('Identification Form'!F106="","",'Identification Form'!F106) | E14: =IF('Identification Form'!G106="","",'Identification Form'!G106) | F14: =IF('Identification Form'!H106="","",'Identification Form'!H106) | J14: =IF('Identification Form'!I106="","",'Identification Form'!I106) | K14: =IF(OR(J14="",I14=""),"",I14-J14) | L14: =IF(AND(H14="",I14=""),"",IF(H14="","local amount missing / chybí částka v místní měně",IF(I14="","CZK amount missing / chybí částka v Kč","")))
A15: 10 | B15: =IF('Identification Form'!B107="","",'Identification Form'!B107) | D15: =IF('Identification Form'!F107="","",'Identification Form'!F107) | E15: =IF('Identification Form'!G107="","",'Identification Form'!G107) | F15: =IF('Identification Form'!H107="","",'Identification Form'!H107) | J15: =IF('Identification Form'!I107="","",'Identification Form'!I107) | K15: =IF(OR(J15="",I15=""),"",I15-J15) | L15: =IF(AND(H15="",I15=""),"",IF(H15="","local amount missing / chybí částka v místní měně",IF(I15="","CZK amount missing / chybí částka v Kč","")))
A16: 11 | B16: =IF('Identification Form'!B108="","",'Identification Form'!B108) | D16: =IF('Identification Form'!F108="","",'Identification Form'!F108) | E16: =IF('Identification Form'!G108="","",'Identification Form'!G108) | F16: =IF('Identification Form'!H108="","",'Identification Form'!H108) | J16: =IF('Identification Form'!I108="","",'Identification Form'!I108) | K16: =IF(OR(J16="",I16=""),"",I16-J16) | L16: =IF(AND(H16="",I16=""),"",IF(H16="","local amount missing / chybí částka v místní měně",IF(I16="","CZK amount missing / chybí částka v Kč","")))
A17: 12 | B17: =IF('Identification Form'!B109="","",'Identification Form'!B109) | D17: =IF('Identification Form'!F109="","",'Identification Form'!F109) | E17: =IF('Identification Form'!G109="","",'Identification Form'!G109) | F17: =IF('Identification Form'!H109="","",'Identification Form'!H109) | J17: =IF('Identification Form'!I109="","",'Identification Form'!I109) | K17: =IF(OR(J17="",I17=""),"",I17-J17) | L17: =IF(AND(H17="",I17=""),"",IF(H17="","local amount missing / chybí částka v místní měně",IF(I17="","CZK amount missing / chybí částka v Kč","")))
... A19: 14 | B19: =IF('Identification Form'!B111="","",'Identification Form'!B111) | D19: =IF('Identification Form'!F111="","",'Identification Form'!F111) | E19: =IF('Identification Form'!G111="","",'Identification Form'!G111) | F19: =IF('Identification Form'!H111="","",'Identification Form'!H111) | J19: =IF('Identification Form'!I111="","",'Identification Form'!I111) | K19: =IF(OR(J19="",I19=""),"",I19-J19) | L19: =IF(AND(H19="",I19=""),"",IF(H19="","local amount missing / chybí částka v místní měně",IF(I19="","CZK amount missing / chybí částka v Kč","")))
A20: Subtotal — Material, Goods and Equipment, including their transport and installation Mezisoučet — Materiál, zboží a vybavení včetně jejich dopravy a instalace | F20: =SUM(F6:F19) -> 29400 | H20: =SUM(H6:H19) -> 0 | I20: =SUM(I6:I19) -> 0 | J20: =SUM(J6:J19) -> 367380.6 | K20: =IF($I$65=0,"",I20-J20) | L20: =IF(OR(F20=0,$I$65=0),"",IF(H20<>F20,"change — describe in Final Report, section 5 / změna — popište v bodě 5 závěrečné zprávy",""))
A21: A.2 Construction and Craft Works A.2 Stavební a řemeslné práce
A22: 1 | B22: =IF('Identification Form'!B114="","",'Identification Form'!B114) | D22: =IF('Identification Form'!F114="","",'Identification Form'!F114) | E22: =IF('Identification Form'!G114="","",'Identification Form'!G114) | F22: =IF('Identification Form'!H114="","",'Identification Form'!H114) | J22: =IF('Identification Form'!I114="","",'Identification Form'!I114) | K22: =IF(OR(J22="",I22=""),"",I22-J22) | L22: =IF(AND(H22="",I22=""),"",IF(H22="","local amount missing / chybí částka v místní měně",IF(I22="","CZK amount missing / chybí částka v Kč","")))
A23: 2 | B23: =IF('Identification Form'!B115="","",'Identification Form'!B115) | D23: =IF('Identification Form'!F115="","",'Identification Form'!F115) | E23: =IF('Identification Form'!G115="","",'Identification Form'!G115) | F23: =IF('Identification Form'!H115="","",'Identification Form'!H115) | J23: =IF('Identification Form'!I115="","",'Identification Form'!I115) | K23: =IF(OR(J23="",I23=""),"",I23-J23) | L23: =IF(AND(H23="",I23=""),"",IF(H23="","local amount missing / chybí částka v místní měně",IF(I23="","CZK amount missing / chybí částka v Kč","")))
A24: 3 | B24: =IF('Identification Form'!B116="","",'Identification Form'!B116) | D24: =IF('Identification Form'!F116="","",'Identification Form'!F116) | E24: =IF('Identification Form'!G116="","",'Identification Form'!G116) | F24: =IF('Identification Form'!H116="","",'Identification Form'!H116) | J24: =IF('Identification Form'!I116="","",'Identification Form'!I116) | K24: =IF(OR(J24="",I24=""),"",I24-J24) | L24: =IF(AND(H24="",I24=""),"",IF(H24="","local amount missing / chybí částka v místní měně",IF(I24="","CZK amount missing / chybí částka v Kč","")))
A25: 4 | B25: =IF('Identification Form'!B117="","",'Identification Form'!B117) | D25: =IF('Identification Form'!F117="","",'Identification Form'!F117) | E25: =IF('Identification Form'!G117="","",'Identification Form'!G117) | F25: =IF('Identification Form'!H117="","",'Identification Form'!H117) | J25: =IF('Identification Form'!I117="","",'Identification Form'!I117) | K25: =IF(OR(J25="",I25=""),"",I25-J25) | L25: =IF(AND(H25="",I25=""),"",IF(H25="","local amount missing / chybí částka v místní měně",IF(I25="","CZK amount missing / chybí částka v Kč","")))
A26: 5 | B26: =IF('Identification Form'!B118="","",'Identification Form'!B118) | D26: =IF('Identification Form'!F118="","",'Identification Form'!F118) | E26: =IF('Identification Form'!G118="","",'Identification Form'!G118) | F26: =IF('Identification Form'!H118="","",'Identification Form'!H118) | J26: =IF('Identification Form'!I118="","",'Identification Form'!I118) | K26: =IF(OR(J26="",I26=""),"",I26-J26) | L26: =IF(AND(H26="",I26=""),"",IF(H26="","local amount missing / chybí částka v místní měně",IF(I26="","CZK amount missing / chybí částka v Kč","")))
A27: 6 | B27: =IF('Identification Form'!B119="","",'Identification Form'!B119) | D27: =IF('Identification Form'!F119="","",'Identification Form'!F119) | E27: =IF('Identification Form'!G119="","",'Identification Form'!G119) | F27: =IF('Identification Form'!H119="","",'Identification Form'!H119) | J27: =IF('Identification Form'!I119="","",'Identification Form'!I119) | K27: =IF(OR(J27="",I27=""),"",I27-J27) | L27: =IF(AND(H27="",I27=""),"",IF(H27="","local amount missing / chybí částka v místní měně",IF(I27="","CZK amount missing / chybí částka v Kč","")))
A28: Subtotal — Construction and Craft Works Mezisoučet — Stavební a řemeslné práce | F28: =SUM(F22:F27) -> 0 | H28: =SUM(H22:H27) -> 0 | I28: =SUM(I22:I27) -> 0 | J28: =SUM(J22:J27) -> 0 | K28: =IF($I$65=0,"",I28-J28) | L28: =IF(OR(F28=0,$I$65=0),"",IF(H28<>F28,"change — describe in Final Report, section 5 / změna — popište v bodě 5 závěrečné zprávy",""))
A29: A.3 Fees of Lecturers, Trainers, Experts and Other Persons Whose Work Is Itself an Output of the Project A.3 Odměny lektorů, školitelů, expertů a dalších osob, jejichž práce je sama výstupem projektu
A30: 1 | B30: =IF('Identification Form'!B122="","",'Identification Form'!B122) -> Lead instructor fee — SSI Diver Stress & Rescue course | D30: =IF('Identification Form'!F122="","",'Identification Form'!F122) -> 1 | E30: =IF('Identification Form'!G122="","",'Identification Form'!G122) -> 600 | F30: =IF('Identification Form'!H122="","",'Identification Form'!H122) -> 600 | J30: =IF('Identification Form'!I122="","",'Identification Form'!I122) -> 7497.5633 | K30: =IF(OR(J30="",I30=""),"",I30-J30) | L30: =IF(AND(H30="",I30=""),"",IF(H30="","local amount missing / chybí částka v místní měně",IF(I30="","CZK amount missing / chybí částka v Kč","")))
A31: 2 | B31: =IF('Identification Form'!B123="","",'Identification Form'!B123) -> Instructor fee — SSI React Right (first aid, CPR, AED, oxygen) course | D31: =IF('Identification Form'!F123="","",'Identification Form'!F123) -> 1 | E31: =IF('Identification Form'!G123="","",'Identification Form'!G123) -> 400 | F31: =IF('Identification Form'!H123="","",'Identification Form'!H123) -> 400 | J31: =IF('Identification Form'!I123="","",'Identification Form'!I123) -> 4998.3755 | K31: =IF(OR(J31="",I31=""),"",I31-J31) | L31: =IF(AND(H31="",I31=""),"",IF(H31="","local amount missing / chybí částka v místní měně",IF(I31="","CZK amount missing / chybí částka v Kč","")))
A32: 3 | B32: =IF('Identification Form'!B124="","",'Identification Form'!B124) | D32: =IF('Identification Form'!F124="","",'Identification Form'!F124) | E32: =IF('Identification Form'!G124="","",'Identification Form'!G124) | F32: =IF('Identification Form'!H124="","",'Identification Form'!H124) | J32: =IF('Identification Form'!I124="","",'Identification Form'!I124) | K32: =IF(OR(J32="",I32=""),"",I32-J32) | L32: =IF(AND(H32="",I32=""),"",IF(H32="","local amount missing / chybí částka v místní měně",IF(I32="","CZK amount missing / chybí částka v Kč","")))
A33: 4 | B33: =IF('Identification Form'!B125="","",'Identification Form'!B125) | D33: =IF('Identification Form'!F125="","",'Identification Form'!F125) | E33: =IF('Identification Form'!G125="","",'Identification Form'!G125) | F33: =IF('Identification Form'!H125="","",'Identification Form'!H125) | J33: =IF('Identification Form'!I125="","",'Identification Form'!I125) | K33: =IF(OR(J33="",I33=""),"",I33-J33) | L33: =IF(AND(H33="",I33=""),"",IF(H33="","local amount missing / chybí částka v místní měně",IF(I33="","CZK amount missing / chybí částka v Kč","")))
A34: 5 | B34: =IF('Identification Form'!B126="","",'Identification Form'!B126) | D34: =IF('Identification Form'!F126="","",'Identification Form'!F126) | E34: =IF('Identification Form'!G126="","",'Identification Form'!G126) | F34: =IF('Identification Form'!H126="","",'Identification Form'!H126) | J34: =IF('Identification Form'!I126="","",'Identification Form'!I126) | K34: =IF(OR(J34="",I34=""),"",I34-J34) | L34: =IF(AND(H34="",I34=""),"",IF(H34="","local amount missing / chybí částka v místní měně",IF(I34="","CZK amount missing / chybí částka v Kč","")))
A35: 6 | B35: =IF('Identification Form'!B127="","",'Identification Form'!B127) | D35: =IF('Identification Form'!F127="","",'Identification Form'!F127) | E35: =IF('Identification Form'!G127="","",'Identification Form'!G127) | F35: =IF('Identification Form'!H127="","",'Identification Form'!H127) | J35: =IF('Identification Form'!I127="","",'Identification Form'!I127) | K35: =IF(OR(J35="",I35=""),"",I35-J35) | L35: =IF(AND(H35="",I35=""),"",IF(H35="","local amount missing / chybí částka v místní měně",IF(I35="","CZK amount missing / chybí částka v Kč","")))
A36: Subtotal — Fees of Lecturers, Trainers, Experts and Other Persons Whose Work Is Itself an Output of the Project Mezisoučet — Odměny lektorů, školitelů, expertů a dalších osob, jejichž práce je sama výstupem projektu | F36: =SUM(F30:F35) -> 1000 | H36: =SUM(H30:H35) -> 0 | I36: =SUM(I30:I35) -> 0 | J36: =SUM(J30:J35) -> 12495.939 | K36: =IF($I$65=0,"",I36-J36) | L36: =IF(OR(F36=0,$I$65=0),"",IF(H36<>F36,"change — describe in Final Report, section 5 / změna — popište v bodě 5 závěrečné zprávy",""))
A37: A.4 Costs of the Participants of Training Provided by the Project A.4 Náklady účastníků školení poskytovaného projektem
A38: 1 | B38: =IF('Identification Form'!B130="","",'Identification Form'!B130) -> SSI Diver Stress & Rescue student kit and certification | D38: =IF('Identification Form'!F130="","",'Identification Form'!F130) -> 15 | E38: =IF('Identification Form'!G130="","",'Identification Form'!G130) -> 200 | F38: =IF('Identification Form'!H130="","",'Identification Form'!H130) -> 3000 | J38: =IF('Identification Form'!I130="","",'Identification Form'!I130) -> 37487.816 | K38: =IF(OR(J38="",I38=""),"",I38-J38) | L38: =IF(AND(H38="",I38=""),"",IF(H38="","local amount missing / chybí částka v místní měně",IF(I38="","CZK amount missing / chybí částka v Kč","")))
A39: 2 | B39: =IF('Identification Form'!B131="","",'Identification Form'!B131) -> SSI React Right student kit and certification | D39: =IF('Identification Form'!F131="","",'Identification Form'!F131) -> 15 | E39: =IF('Identification Form'!G131="","",'Identification Form'!G131) -> 140 | F39: =IF('Identification Form'!H131="","",'Identification Form'!H131) -> 2100 | J39: =IF('Identification Form'!I131="","",'Identification Form'!I131) -> 26241.472 | K39: =IF(OR(J39="",I39=""),"",I39-J39) | L39: =IF(AND(H39="",I39=""),"",IF(H39="","local amount missing / chybí částka v místní měně",IF(I39="","CZK amount missing / chybí částka v Kč","")))
A40: 3 | B40: =IF('Identification Form'!B132="","",'Identification Form'!B132) -> Open-water training logistics (tank fills, site access) | D40: =IF('Identification Form'!F132="","",'Identification Form'!F132) -> 4 | E40: =IF('Identification Form'!G132="","",'Identification Form'!G132) -> 100 | F40: =IF('Identification Form'!H132="","",'Identification Form'!H132) -> 400 | J40: =IF('Identification Form'!I132="","",'Identification Form'!I132) -> 4998.3755 | K40: =IF(OR(J40="",I40=""),"",I40-J40) | L40: =IF(AND(H40="",I40=""),"",IF(H40="","local amount missing / chybí částka v místní měně",IF(I40="","CZK amount missing / chybí částka v Kč","")))
A41: 4 | B41: =IF('Identification Form'!B133="","",'Identification Form'!B133) | D41: =IF('Identification Form'!F133="","",'Identification Form'!F133) | E41: =IF('Identification Form'!G133="","",'Identification Form'!G133) | F41: =IF('Identification Form'!H133="","",'Identification Form'!H133) | J41: =IF('Identification Form'!I133="","",'Identification Form'!I133) | K41: =IF(OR(J41="",I41=""),"",I41-J41) | L41: =IF(AND(H41="",I41=""),"",IF(H41="","local amount missing / chybí částka v místní měně",IF(I41="","CZK amount missing / chybí částka v Kč","")))
A42: Subtotal — Costs of the Participants of Training Provided by the Project Mezisoučet — Náklady účastníků školení poskytovaného projektem | F42: =SUM(F38:F41) -> 5500 | H42: =SUM(H38:H41) -> 0 | I42: =SUM(I38:I41) -> 0 | J42: =SUM(J38:J41) -> 68727.664 | K42: =IF($I$65=0,"",I42-J42) | L42: =IF(OR(F42=0,$I$65=0),"",IF(H42<>F42,"change — describe in Final Report, section 5 / změna — popište v bodě 5 závěrečné zprávy",""))
A43: SUBTOTAL A — PROJECT COSTS MEZISOUČET A — PROJEKTOVÉ NÁKLADY | F43: =F20+F28+F36+F42 -> 35900 | H43: =H20+H28+H36+H42 -> 0 | I43: =I20+I28+I36+I42 -> 0 | J43: =J20+J28+J36+J42 -> 448604.2 | K43: =IF($I$65=0,"",I43-J43)
A44: B. SUPPORT COSTS B. PODPŮRNÉ NÁKLADY
A45: B.1 Salaries, Fees and Per Diems of the Project Manager and of the Administrative Staff of the Implementer B.1 Mzdy, odměny a diety projektového manažera a administrativních pracovníků realizátora
A46: 1 | B46: =IF('Identification Form'!B138="","",'Identification Form'!B138) -> Project manager honorarium (part-time, project duration) | D46: =IF('Identification Form'!F138="","",'Identification Form'!F138) -> 1 | E46: =IF('Identification Form'!G138="","",'Identification Form'!G138) -> 600 | F46: =IF('Identification Form'!H138="","",'Identification Form'!H138) -> 600 | J46: =IF('Identification Form'!I138="","",'Identification Form'!I138) -> 7497.5633 | K46: =IF(OR(J46="",I46=""),"",I46-J46) | L46: =IF(AND(H46="",I46=""),"",IF(H46="","local amount missing / chybí částka v místní měně",IF(I46="","CZK amount missing / chybí částka v Kč","")))
A47: 2 | B47: =IF('Identification Form'!B139="","",'Identification Form'!B139) | D47: =IF('Identification Form'!F139="","",'Identification Form'!F139) | E47: =IF('Identification Form'!G139="","",'Identification Form'!G139) | F47: =IF('Identification Form'!H139="","",'Identification Form'!H139) | J47: =IF('Identification Form'!I139="","",'Identification Form'!I139) | K47: =IF(OR(J47="",I47=""),"",I47-J47) | L47: =IF(AND(H47="",I47=""),"",IF(H47="","local amount missing / chybí částka v místní měně",IF(I47="","CZK amount missing / chybí částka v Kč","")))
A48: 3 | B48: =IF('Identification Form'!B140="","",'Identification Form'!B140) | D48: =IF('Identification Form'!F140="","",'Identification Form'!F140) | E48: =IF('Identification Form'!G140="","",'Identification Form'!G140) | F48: =IF('Identification Form'!H140="","",'Identification Form'!H140) | J48: =IF('Identification Form'!I140="","",'Identification Form'!I140) | K48: =IF(OR(J48="",I48=""),"",I48-J48) | L48: =IF(AND(H48="",I48=""),"",IF(H48="","local amount missing / chybí částka v místní měně",IF(I48="","CZK amount missing / chybí částka v Kč","")))
A49: 4 | B49: =IF('Identification Form'!B141="","",'Identification Form'!B141) | D49: =IF('Identification Form'!F141="","",'Identification Form'!F141) | E49: =IF('Identification Form'!G141="","",'Identification Form'!G141) | F49: =IF('Identification Form'!H141="","",'Identification Form'!H141) | J49: =IF('Identification Form'!I141="","",'Identification Form'!I141) | K49: =IF(OR(J49="",I49=""),"",I49-J49) | L49: =IF(AND(H49="",I49=""),"",IF(H49="","local amount missing / chybí částka v místní měně",IF(I49="","CZK amount missing / chybí částka v Kč","")))
A50: 5 | B50: =IF('Identification Form'!B142="","",'Identification Form'!B142) | D50: =IF('Identification Form'!F142="","",'Identification Form'!F142) | E50: =IF('Identification Form'!G142="","",'Identification Form'!G142) | F50: =IF('Identification Form'!H142="","",'Identification Form'!H142) | J50: =IF('Identification Form'!I142="","",'Identification Form'!I142) | K50: =IF(OR(J50="",I50=""),"",I50-J50) | L50: =IF(AND(H50="",I50=""),"",IF(H50="","local amount missing / chybí částka v místní měně",IF(I50="","CZK amount missing / chybí částka v Kč","")))
A51: Subtotal — Salaries, Fees and Per Diems of the Project Manager and of the Administrative Staff of the Implementer Mezisoučet — Mzdy, odměny a diety projektového manažera a administrativních pracovníků realizátora | F51: =SUM(F46:F50) -> 600 | H51: =SUM(H46:H50) -> 0 | I51: =SUM(I46:I50) -> 0 | J51: =SUM(J46:J50) -> 7497.5633 | K51: =IF($I$65=0,"",I51-J51) | L51: =IF(OR(F51=0,$I$65=0),"",IF(H51<>F51,"change — describe in Final Report, section 5 / změna — popište v bodě 5 závěrečné zprávy",""))
A52: B.2 Travel, Accommodation, Insurance and Vaccination of the Staff Listed under B.1 B.2 Cestovné, ubytování, pojištění a očkování pracovníků uvedených v bodě B.1
A53: 1 | B53: =IF('Identification Form'!B145="","",'Identification Form'!B145) -> Local travel for project preparation and monitoring | D53: =IF('Identification Form'!F145="","",'Identification Form'!F145) -> 1 | E53: =IF('Identification Form'!G145="","",'Identification Form'!G145) -> 120 | F53: =IF('Identification Form'!H145="","",'Identification Form'!H145) -> 120 | J53: =IF('Identification Form'!I145="","",'Identification Form'!I145) -> 1499.5127 | K53: =IF(OR(J53="",I53=""),"",I53-J53) | L53: =IF(AND(H53="",I53=""),"",IF(H53="","local amount missing / chybí částka v místní měně",IF(I53="","CZK amount missing / chybí částka v Kč","")))
A54: 2 | B54: =IF('Identification Form'!B146="","",'Identification Form'!B146) | D54: =IF('Identification Form'!F146="","",'Identification Form'!F146) | E54: =IF('Identification Form'!G146="","",'Identification Form'!G146) | F54: =IF('Identification Form'!H146="","",'Identification Form'!H146) | J54: =IF('Identification Form'!I146="","",'Identification Form'!I146) | K54: =IF(OR(J54="",I54=""),"",I54-J54) | L54: =IF(AND(H54="",I54=""),"",IF(H54="","local amount missing / chybí částka v místní měně",IF(I54="","CZK amount missing / chybí částka v Kč","")))
A55: 3 | B55: =IF('Identification Form'!B147="","",'Identification Form'!B147) | D55: =IF('Identification Form'!F147="","",'Identification Form'!F147) | E55: =IF('Identification Form'!G147="","",'Identification Form'!G147) | F55: =IF('Identification Form'!H147="","",'Identification Form'!H147) | J55: =IF('Identification Form'!I147="","",'Identification Form'!I147) | K55: =IF(OR(J55="",I55=""),"",I55-J55) | L55: =IF(AND(H55="",I55=""),"",IF(H55="","local amount missing / chybí částka v místní měně",IF(I55="","CZK amount missing / chybí částka v Kč","")))
A56: 4 | B56: =IF('Identification Form'!B148="","",'Identification Form'!B148) | D56: =IF('Identification Form'!F148="","",'Identification Form'!F148) | E56: =IF('Identification Form'!G148="","",'Identification Form'!G148) | F56: =IF('Identification Form'!H148="","",'Identification Form'!H148) | J56: =IF('Identification Form'!I148="","",'Identification Form'!I148) | K56: =IF(OR(J56="",I56=""),"",I56-J56) | L56: =IF(AND(H56="",I56=""),"",IF(H56="","local amount missing / chybí částka v místní měně",IF(I56="","CZK amount missing / chybí částka v Kč","")))
A57: Subtotal — Travel, Accommodation, Insurance and Vaccination of the Staff Listed under B.1 Mezisoučet — Cestovné, ubytování, pojištění a očkování pracovníků uvedených v bodě B.1 | F57: =SUM(F53:F56) -> 120 | H57: =SUM(H53:H56) -> 0 | I57: =SUM(I53:I56) -> 0 | J57: =SUM(J53:J56) -> 1499.5127 | K57: =IF($I$65=0,"",I57-J57) | L57: =IF(OR(F57=0,$I$65=0),"",IF(H57<>F57,"change — describe in Final Report, section 5 / změna — popište v bodě 5 závěrečné zprávy",""))
A58: B.3 Translations, Bank Charges and Publicity of the Project B.3 Překlady, bankovní poplatky a propagace projektu
A59: 1 | B59: =IF('Identification Form'!B151="","",'Identification Form'!B151) -> Bank charges, translation of reports, promotional materials (logo plaques, banners) | D59: =IF('Identification Form'!F151="","",'Identification Form'!F151) -> 1 | E59: =IF('Identification Form'!G151="","",'Identification Form'!G151) -> 350 | F59: =IF('Identification Form'!H151="","",'Identification Form'!H151) -> 350 | J59: =IF('Identification Form'!I151="","",'Identification Form'!I151) -> 4373.5786 | K59: =IF(OR(J59="",I59=""),"",I59-J59) | L59: =IF(AND(H59="",I59=""),"",IF(H59="","local amount missing / chybí částka v místní měně",IF(I59="","CZK amount missing / chybí částka v Kč","")))
A60: 2 | B60: =IF('Identification Form'!B152="","",'Identification Form'!B152) | D60: =IF('Identification Form'!F152="","",'Identification Form'!F152) | E60: =IF('Identification Form'!G152="","",'Identification Form'!G152) | F60: =IF('Identification Form'!H152="","",'Identification Form'!H152) | J60: =IF('Identification Form'!I152="","",'Identification Form'!I152) | K60: =IF(OR(J60="",I60=""),"",I60-J60) | L60: =IF(AND(H60="",I60=""),"",IF(H60="","local amount missing / chybí částka v místní měně",IF(I60="","CZK amount missing / chybí částka v Kč","")))
A61: 3 | B61: =IF('Identification Form'!B153="","",'Identification Form'!B153) | D61: =IF('Identification Form'!F153="","",'Identification Form'!F153) | E61: =IF('Identification Form'!G153="","",'Identification Form'!G153) | F61: =IF('Identification Form'!H153="","",'Identification Form'!H153) | J61: =IF('Identification Form'!I153="","",'Identification Form'!I153) | K61: =IF(OR(J61="",I61=""),"",I61-J61) | L61: =IF(AND(H61="",I61=""),"",IF(H61="","local amount missing / chybí částka v místní měně",IF(I61="","CZK amount missing / chybí částka v Kč","")))
A62: 4 | B62: =IF('Identification Form'!B154="","",'Identification Form'!B154) | D62: =IF('Identification Form'!F154="","",'Identification Form'!F154) | E62: =IF('Identification Form'!G154="","",'Identification Form'!G154) | F62: =IF('Identification Form'!H154="","",'Identification Form'!H154) | J62: =IF('Identification Form'!I154="","",'Identification Form'!I154) | K62: =IF(OR(J62="",I62=""),"",I62-J62) | L62: =IF(AND(H62="",I62=""),"",IF(H62="","local amount missing / chybí částka v místní měně",IF(I62="","CZK amount missing / chybí částka v Kč","")))
A63: Subtotal — Translations, Bank Charges and Publicity of the Project Mezisoučet — Překlady, bankovní poplatky a propagace projektu | F63: =SUM(F59:F62) -> 350 | H63: =SUM(H59:H62) -> 0 | I63: =SUM(I59:I62) -> 0 | J63: =SUM(J59:J62) -> 4373.5786 | K63: =IF($I$65=0,"",I63-J63) | L63: =IF(OR(F63=0,$I$65=0),"",IF(H63<>F63,"change — describe in Final Report, section 5 / změna — popište v bodě 5 závěrečné zprávy",""))
A64: SUBTOTAL B — SUPPORT COSTS MEZISOUČET B — PODPŮRNÉ NÁKLADY | F64: =F51+F57+F63 -> 1070 | H64: =H51+H57+H63 -> 0 | I64: =I51+I57+I63 -> 0 | J64: =J51+J57+J63 -> 13370.655 | K64: =IF($I$65=0,"",I64-J64)
A65: GRAND TOTAL actually spent CELKEM skutečně vyčerpáno | F65: =F43+F64 -> 36970 | H65: =H43+H64 -> 0 | I65: =I43+I64 -> 0 | J65: =J43+J64 -> 461974.86 | K65: =IF($I$65=0,"",I65-J65) | L65: =IF(I71="","",I71)
A66: Automatic checks Automatické kontroly
A67: Approved in CZK including the exchange rate reserve (contract amount) Schváleno v Kč včetně kurzové rezervy (smluvní částka) | F67: =IF('Identification Form'!I173="","",'Identification Form'!I173) -> 475834.1
A68: Unspent amount to be returned to the Embassy (CZK) Nevyčerpaná částka k vrácení velvyslanectví (Kč) | F68: =IF(OR(F67="",F67=0,I65=0,I65=""),"",MAX(0,F67-I65)) | G68: =IF(OR(I65=0,F67="",I65=""),"",IF(I65>F67,"ACTUAL SPENDING EXCEEDS THE APPROVED AMOUNT / SKUTEČNÉ ČERPÁNÍ PŘEKRAČUJE SCHVÁLENOU ČÁSTKU",""))
A69: Support costs (block B) as a share of actual spending — limit 8 % Podpůrné náklady (blok B) jako podíl na skutečném čerpání — limit 8 % | F69: =I64 -> 0 | G69: =IF(I65=0,"",F69/I65) | I69: =IF(I65=0,"",IF(G69>0.08,"EXCEEDS THE 8 % LIMIT / PŘEKRAČUJE LIMIT 8 %","within limit / v limitu"))
A70: Exchange rate reserve actually drawn (CZK) Skutečně čerpaná kurzová rezerva (Kč) | F70: =IF(OR(I65="",I65=0,'Identification Form'!I157=0),"",MAX(0,I65-'Identification Form'!I157)) | G70: Not a change of the budget; shown in section 1 of the Final Report. Nejde o změnu rozpočtu; uvádí se v bodě 1 závěrečné zprávy.
A71: Budget change** — increases of budget lines in CZK vs. the approved Identification Form, as a share of the approved budget excl. the reserve — limit 10 % Změna rozpočtu** — navýšení rozpočtových položek v Kč oproti schválenému identifikačnímu formuláři, jako podíl na schváleném rozpočtu bez rezervy — limit 10 % | F71: =IF($I$65=0,"",SUMIF(K6:K19,">0")+SUMIF(K22:K27,">0")+SUMIF(K30:K35,">0")+SUMIF(K38:K41,">0")+SUMIF(K46:K50,">0")+SUMIF(K53:K56,">0")+SUMIF(K59:K62,">0")) | G71: =IF(OR(F71="",'Identification Form'!I157=0),"",F71/'Identification Form'!I157) | I71: =IF(G71="","",IF(F71=0,"no budget change / bez změny rozpočtu",IF(G71>0.1,"ABOVE 10 % — APPROVED CHANGE REQUEST REQUIRED / NAD 10 % — NUTNÁ SCHVÁLENÁ ŽÁDOST O ZMĚNU","up to 10 % — prior notification was sufficient / do 10 % — stačilo předchozí oznámení")))
A72: Additional funding from other sources Další zdroje financování
A73: Informative only — does not affect the Czech funding Pouze informativní — neovlivňuje české financování | F73: Planned (local) Plánováno (místní měna) | G73: Actually used (local) Skutečně použito (místní měna)
A74: TOTAL additional funding from other sources CELKEM další zdroje financování | F74: ='Identification Form'!H168 -> 5000
A75: * The total of block B (support costs) must not exceed 8 % of the amount provided from the Czech Republic Official Development Assistance. * Součet bloku B (podpůrné náklady) nesmí přesáhnout 8 % částky poskytnuté ze zahraniční rozvojové spolupráce České republiky.
A76: ** A budget change is the sum of the increases of the individual budget lines in CZK compared with the approved Identification Form (the original one or, after an approved change, the revised one), using the exchange rates communicated by the Embassy; each amount moved is counted once, decreases and the exchange rate reserve are not counted. Changes that in aggregate did not exceed 10 % of the approved budget (excluding the exchange rate reserve) only had to be notified to the Embassy in writing in advance; changes above 10 % required a written change request approved by the Embassy in advance (no contract amendment is concluded). The check above shows the result. If it shows "approved change request required", the number and date of the approved change request must be stated in section 5 of the Final Report; smaller changes must also be described there. Any change of activities or outputs required prior approval regardless of the amount. ** Změnou rozpočtu se rozumí souhrn navýšení jednotlivých rozpočtových položek v Kč oproti schválenému identifikačnímu formuláři (původnímu, nebo po schválené změně upravenému), přepočtený kurzy sdělenými velvyslanectvím; každá přesunutá částka se počítá jednou, snížení položek a kurzová rezerva se nezapočítávají. Změny, které v souhrnu nepřesáhly 10 % schváleného rozpočtu (bez kurzové rezervy), stačilo velvyslanectví předem písemně oznámit; změny nad 10 % vyžadovaly písemnou žádost o změnu předem schválenou velvyslanectvím (dodatek ke smlouvě se neuzavírá). Výsledek ukazuje kontrola výše. Ukazuje-li „nutná schválená žádost o změnu“, musí být v bodě 5 závěrečné zprávy uvedeno číslo a datum schválené žádosti; menší změny je tam rovněž nutné popsat. Jakákoli změna aktivit nebo výstupů vyžadovala předchozí schválení bez ohledu na výši částky.
A77: Signature of the implementer Podpis realizátora
A78: Done in (city) Vyhotoveno v (město)
A79: Date Datum
A80: Signed by (name and position of the authorised person) Podepisuje (jméno a funkce oprávněné osoby)
A81: Telephone Telefon
A82: Email Address E-mailová adresa
A83: Signature Podpis
A84: Both reports — the Final Report sheet and this Financial Report sheet — must be signed by the authorised person of the implementer before submission, in the same manner as the Identification Form (electronic signature, or handwritten signature delivered in paper form or as a scan). Obě zprávy — list Závěrečná zpráva i tento list Finanční zpráva — musí být před odesláním velvyslanectví podepsány oprávněnou osobou realizátora stejným způsobem jako identifikační formulář (elektronický podpis, nebo vlastnoruční podpis doručený v listinné podobě či ve formě skenu).

Sheet Final Report
A1: Final Report on Small Scale Project Implementation Závěrečná zpráva o realizaci malého lokálního projektu
A2: THIS SHEET IS COMPLETED ONLY FOR AN APPROVED PROJECT, AFTER THE IMPLEMENTATION HAS BEEN COMPLETED — including cases where the project ended earlier than planned. It is submitted to the Embassy within one month of the completion of the project but no later than 15 November of the relevant year, together with the Financial Report and the photographs of the marked outputs. BOTH the Final Report and the Financial Report must be SIGNED by the authorised person of the implementer before submission — electronically, or by hand and delivered in paper form or as a scan; unsigned reports cannot be accepted. Grey cells are taken from the Identification Form and from the Financial Report; fill in the white cells only. TENTO LIST SE VYPLŇUJE POUZE U SCHVÁLENÉHO PROJEKTU, A TO AŽ PO UKONČENÍ REALIZACE — včetně případů, kdy projekt skončil dříve, než bylo plánováno. Velvyslanectví se předkládá do jednoho měsíce od ukončení projektu, nejpozději však do 15. listopadu příslušného roku, spolu s finanční zprávou a fotografiemi označených výstupů. Závěrečná zpráva I finanční zpráva musí být před odesláním PODEPSÁNY oprávněnou osobou realizátora — elektronicky, nebo vlastnoručně s doručením v listinné podobě či ve formě skenu; nepodepsané zprávy nelze přijmout. Šedé buňky se přebírají z identifikačního formuláře a z finanční zprávy; vyplňujte pouze bílé buňky.
A3: Project Title Název projektu | C3: =IF('Identification Form'!C3="","",'Identification Form'!C3) -> Safe Waters – Youth Water Rescue Training and Response Unit | G3: Project Number Číslo projektu | I3: =IF('Identification Form'!I3="","",'Identification Form'!I3)
A4: Country Země | C4: =IF('Identification Form'!C4="","",'Identification Form'!C4) -> Bosnia and Herzegovina | G4: Project Location Místo realizace | I4: =IF('Identification Form'!I4="","",'Identification Form'!I4) -> Sarajevo (club headquarters); Jablaničko Lake (rescue boat base) and Boračko Lake, Konjic Municipality, Herzegovina-Neretva Canton
A5: Planned beginning Plánované zahájení | C5: =IF('Identification Form'!C5="","",'Identification Form'!C5) -> April 2027 | G5: Planned termination Plánované ukončení | I5: =IF('Identification Form'!I5="","",'Identification Form'!I5) -> October 2027
A6: Actual beginning (month / year) Skutečné zahájení (měsíc / rok) | G6: Actual termination (month / year) Skutečné ukončení (měsíc / rok)
A7: Was the implementation terminated earlier than planned? Byla realizace ukončena dříve, než bylo plánováno? | G7: If yes, state the reason Pokud ano, uveďte důvod
A8: 1. Funding 1. Financování
A9: Approved from Czech ODA in CZK including the exchange rate reserve Schváleno ze ZRS ČR v Kč včetně kurzové rezervy | G9: =IF('Identification Form'!I173="","",'Identification Form'!I173) -> 475834.1
A10: Actually spent from Czech ODA in CZK Skutečně vyčerpáno ze ZRS ČR v Kč | G10: =IF('Financial Report'!I65=0,"",'Financial Report'!I65)
A11: Exchange rate reserve actually drawn (CZK) Skutečně čerpaná kurzová rezerva (Kč) | G11: =IF('Financial Report'!F70="","",'Financial Report'!F70)
A12: Unspent amount returned to the Embassy in CZK Nevyčerpaná částka vrácená velvyslanectví v Kč | G12: =IF('Financial Report'!F68="","",'Financial Report'!F68)
A13: Additional funding from other sources actually used (local currency) Skutečně použité prostředky z dalších zdrojů (místní měna) | G13: =IF('Financial Report'!G74=0,"",'Financial Report'!G74)
A14: 2. Implementing Organization 2. Realizující organizace
A15: Name of Organization Název organizace | E15: =IF('Identification Form'!E18="","",'Identification Form'!E18) -> Klub vodenih sportova „S.C.U.B.A.“ Sarajevo (KVS SCUBA)
A16: Acting By and Through (name and position) Zastoupená (jméno a funkce) | E16: =IF('Identification Form'!E188="","",'Identification Form'!E188) -> Adnan Drnda, President of KVS SCUBA
A17: Email Address E-mailová adresa | E17: =IF('Identification Form'!E20="","",'Identification Form'!E20) -> kvsscuba@gmail.com
A18: Contact person for this report (name, telephone) Kontaktní osoba pro tuto zprávu (jméno, telefon)
A19: 3. Target Group Actually Reached 3. Skutečně zasažená cílová skupina
A20: Beneficiaries Příjemci | D20: Planned number Plánovaný počet | F20: Actual number Skutečný počet | H20: % of plan % plánu | I20: Explanation if the number differs from the plan Vysvětlení, pokud se počet liší od plánu
A21: Direct beneficiaries Přímí příjemci | D21: =IF('Identification Form'!E28="","",'Identification Form'!E28) -> 15 | H21: =IF(OR(D21="",D21=0,F21=""),"",F21/D21)
A22: Indirect beneficiaries Nepřímí příjemci | D22: =IF('Identification Form'!E29="","",'Identification Form'!E29) -> 5000 | H22: =IF(OR(D22="",D22=0,F22=""),"",F22/D22)
A23: 4. Activities, Outputs and Indicators 4. Aktivity, výstupy a indikátory
A24: The first four columns are taken from the Identification Form and cannot be edited. Report the value actually achieved for every activity that was planned. The status is calculated automatically. První čtyři sloupce se přebírají z identifikačního formuláře a nelze je upravovat. U každé plánované aktivity uveďte skutečně dosaženou hodnotu. Stav se počítá automaticky.
A25: No. Č. | B25: Activity (planned) Aktivita (plánovaná) | D25: Indicator Indikátor | F25: Target Cíl | G25: Achieved Dosaženo | H25: Status Stav | I25: Explanation if not fully achieved Vysvětlení, pokud nebylo plně dosaženo | K25: Evidence attached Přiložené doklady
A26: 1 | B26: =IF('Identification Form'!B59="","",'Identification Form'!B59) -> Procurement of new electric-powered inflatable boat, electric outboard motor, registration and insurance | D26: =IF('Identification Form'!F59="","",'Identification Form'!F59) -> Number of boats procured and registered | F26: =IF('Identification Form'!H59="","",'Identification Form'!H59) -> 1 | H26: =IF(B26="","",IF(G26="","not reported / nevykázáno",IF(AND(ISNUMBER(F26),ISNUMBER(G26)),IF(G26>=F26,"achieved / splněno",IF(G26>=F26*0.5,"partially achieved / částečně splněno","not achieved / nesplněno")),"see explanation"))) -> not reported / nevykázáno
A27: 2 | B27: =IF('Identification Form'!B60="","",'Identification Form'!B60) -> Procurement of dry suits with undergarments, rescue set (buoys, line, oxygen kit), AED and VHF radios | D27: =IF('Identification Form'!F60="","",'Identification Form'!F60) -> Number of dry suits / rescue sets / AEDs / radios procured | F27: =IF('Identification Form'!H60="","",'Identification Form'!H60) -> 4 / 1 / 1 / 2 | H27: =IF(B27="","",IF(G27="","not reported / nevykázáno",IF(AND(ISNUMBER(F27),ISNUMBER(G27)),IF(G27>=F27,"achieved / splněno",IF(G27>=F27*0.5,"partially achieved / částečně splněno","not achieved / nesplněno")),"see explanation"))) -> not reported / nevykázáno
A28: 3 | B28: =IF('Identification Form'!B61="","",'Identification Form'!B61) -> Adaptation of existing space for secure equipment storage and maintenance; servicing of club compressor, cylinders and regulators (Club-funded) | D28: =IF('Identification Form'!F61="","",'Identification Form'!F61) -> Storage adapted and equipment serviced (yes/no) | F28: =IF('Identification Form'!H61="","",'Identification Form'!H61) -> 1 | H28: =IF(B28="","",IF(G28="","not reported / nevykázáno",IF(AND(ISNUMBER(F28),ISNUMBER(G28)),IF(G28>=F28,"achieved / splněno",IF(G28>=F28*0.5,"partially achieved / částečně splněno","not achieved / nesplněno")),"see explanation"))) -> not reported / nevykázáno
A29: 4 | B29: =IF('Identification Form'!B62="","",'Identification Form'!B62) -> SSI Diver Stress & Rescue course for the same 15 participants | D29: =IF('Identification Form'!F62="","",'Identification Form'!F62) -> Number of participants certified | F29: =IF('Identification Form'!H62="","",'Identification Form'!H62) -> 15 | H29: =IF(B29="","",IF(G29="","not reported / nevykázáno",IF(AND(ISNUMBER(F29),ISNUMBER(G29)),IF(G29>=F29,"achieved / splněno",IF(G29>=F29*0.5,"partially achieved / částečně splněno","not achieved / nesplněno")),"see explanation"))) -> not reported / nevykázáno
A30: 5 | B30: =IF('Identification Form'!B63="","",'Identification Form'!B63) -> SSI React Right course (first aid, CPR, AED, oxygen) for 15 club divers | D30: =IF('Identification Form'!F63="","",'Identification Form'!F63) -> Number of participants certified | F30: =IF('Identification Form'!H63="","",'Identification Form'!H63) -> 15 | H30: =IF(B30="","",IF(G30="","not reported / nevykázáno",IF(AND(ISNUMBER(F30),ISNUMBER(G30)),IF(G30>=F30,"achieved / splněno",IF(G30>=F30*0.5,"partially achieved / částečně splněno","not achieved / nesplněno")),"see explanation"))) -> not reported / nevykázáno
A31: 6 | B31: =IF('Identification Form'!B64="","",'Identification Form'!B64) -> Volunteer duty roster at Jablaničko Lake and Boračko Lake (boat and divers) | D31: =IF('Identification Form'!F64="","",'Identification Form'!F64) -> Number of duty days covered | F31: =IF('Identification Form'!H64="","",'Identification Form'!H64) -> 30 | H31: =IF(B31="","",IF(G31="","not reported / nevykázáno",IF(AND(ISNUMBER(F31),ISNUMBER(G31)),IF(G31>=F31,"achieved / splněno",IF(G31>=F31*0.5,"partially achieved / částečně splněno","not achieved / nesplněno")),"see explanation"))) -> not reported / nevykázáno
A32: 7 | B32: =IF('Identification Form'!B65="","",'Identification Form'!B65) -> Water-safety awareness sessions for local schools and communities | D32: =IF('Identification Form'!F65="","",'Identification Form'!F65) -> Number of people reached | F32: =IF('Identification Form'!H65="","",'Identification Form'!H65) -> 500 | H32: =IF(B32="","",IF(G32="","not reported / nevykázáno",IF(AND(ISNUMBER(F32),ISNUMBER(G32)),IF(G32>=F32,"achieved / splněno",IF(G32>=F32*0.5,"partially achieved / částečně splněno","not achieved / nesplněno")),"see explanation"))) -> not reported / nevykázáno
A33: 8 | B33: =IF('Identification Form'!B66="","",'Identification Form'!B66) -> Public handover and launch event with the Embassy | D33: =IF('Identification Form'!F66="","",'Identification Form'!F66) -> Event held (yes/no) | F33: =IF('Identification Form'!H66="","",'Identification Form'!H66) -> 1 | H33: =IF(B33="","",IF(G33="","not reported / nevykázáno",IF(AND(ISNUMBER(F33),ISNUMBER(G33)),IF(G33>=F33,"achieved / splněno",IF(G33>=F33*0.5,"partially achieved / částečně splněno","not achieved / nesplněno")),"see explanation"))) -> not reported / nevykázáno
A34: 9 | B34: =IF('Identification Form'!B67="","",'Identification Form'!B67) -> Agreement with the local Civil Protection service on availability of the unit's boat, divers and equipment in emergencies | D34: =IF('Identification Form'!F67="","",'Identification Form'!F67) -> Written agreement or protocol signed (yes/no) | F34: =IF('Identification Form'!H67="","",'Identification Form'!H67) -> 1 | H34: =IF(B34="","",IF(G34="","not reported / nevykázáno",IF(AND(ISNUMBER(F34),ISNUMBER(G34)),IF(G34>=F34,"achieved / splněno",IF(G34>=F34*0.5,"partially achieved / částečně splněno","not achieved / nesplněno")),"see explanation"))) -> not reported / nevykázáno
A35: 10 | B35: =IF('Identification Form'!B68="","",'Identification Form'!B68) | D35: =IF('Identification Form'!F68="","",'Identification Form'!F68) | F35: =IF('Identification Form'!H68="","",'Identification Form'!H68) | H35: =IF(B35="","",IF(G35="","not reported / nevykázáno",IF(AND(ISNUMBER(F35),ISNUMBER(G35)),IF(G35>=F35,"achieved / splněno",IF(G35>=F35*0.5,"partially achieved / částečně splněno","not achieved / nesplněno")),"see explanation")))
A36: 5. Changes During Implementation 5. Změny v průběhu realizace
A37: List every change to the activities or the budget compared with the approved Identification Form. A budget change is the sum of the increases of the individual budget lines in CZK (each amount moved counted once; decreases and the exchange rate reserve are not counted). Budget changes that in aggregate did not exceed 10 % of the approved budget (excluding the exchange rate reserve) only had to be notified to the Embassy in writing in advance. Larger budget changes and any change of activities or outputs required a written change request approved by the Embassy in advance; the approved change request with the revised Identification Form replaces the original form. If the Financial Report shows "approved change request required", the number and date of the approved change request must be stated here. Drawing on the exchange rate reserve is not a change of the budget; the amount drawn is shown in section 1. Uveďte každou změnu aktivit nebo rozpočtu oproti schválenému identifikačnímu formuláři. Změnou rozpočtu se rozumí souhrn navýšení jednotlivých rozpočtových položek v Kč (každá přesunutá částka se počítá jednou; snížení položek a kurzová rezerva se nezapočítávají). Změny rozpočtu, které v souhrnu nepřesáhly 10 % schváleného rozpočtu (bez kurzové rezervy), stačilo velvyslanectví předem písemně oznámit. Větší změny rozpočtu a jakákoli změna aktivit nebo výstupů vyžadovaly písemnou žádost o změnu předem schválenou velvyslanectvím; schválená žádost o změnu s upraveným identifikačním formulářem nahrazuje původní formulář. Pokud finanční zpráva ukazuje „nutná schválená žádost o změnu“, musí zde být uvedeno číslo a datum schválené žádosti. Čerpání kurzové rezervy není změnou rozpočtu; čerpaná částka je uvedena v bodě 1.
A38: No. Č. | B38: What was changed (activity or budget line) Co bylo změněno (aktivita nebo rozpočtová položka) | F38: Date of change Datum změny | G38: Type of change Typ změny | I38: Reference (change request No. and date of approval, or notification e-mail / letter) Odkaz (číslo a datum schválení žádosti o změnu, nebo oznamovací e-mail / dopis)
A39: 1
A40: 2
A41: 3
A42: 4
A43: 5
A44: 6
A45: 7
A46: 8
A47: 6. Sustainability and Ownership of the Outputs 6. Udržitelnost a vlastnictví výstupů
A48: Describe the condition of the outputs at handover and how the benefits for the target group will continue. Popište stav výstupů při předání a to, jak budou přínosy pro cílovou skupinu pokračovat.
L49: =LEN(A49)&" / 800" -> 0 / 800
A50: 7. Visibility of Czech Assistance 7. Viditelnost české pomoci
A51: How were the material outputs actually marked with the MFA CZ logo, and how was the support from the Czech Republic stated for the intangible outputs? Jak byly hmotné výstupy skutečně označeny logem MZV ČR a jak byla u nehmotných výstupů uvedena podpora České republiky?
A52: Audience Publikum | F52: Planned number Plánovaný počet | H52: Actual number Skutečný počet | J52: Note Poznámka
A53: =IF('Identification Form'!A85="","",'Identification Form'!A85) -> Local community where the project takes place Místní komunita v místě realizace projektu | F53: =IF('Identification Form'!G85="","",'Identification Form'!G85) -> 5000
A54: =IF('Identification Form'!A86="","",'Identification Form'!A86) -> Staff and users of the partner institution Zaměstnanci a uživatelé partnerské instituce | F54: =IF('Identification Form'!G86="","",'Identification Form'!G86)
A55: =IF('Identification Form'!A87="","",'Identification Form'!A87) -> Local or regional media Místní nebo regionální média | F55: =IF('Identification Form'!G87="","",'Identification Form'!G87) -> 3000
A56: =IF('Identification Form'!A88="","",'Identification Form'!A88) -> Participants of a public event (handover, opening) Účastníci veřejné akce (předání, slavnostní otevření) | F56: =IF('Identification Form'!G88="","",'Identification Form'!G88) -> 80
A57: Number of photographs of the marked outputs attached to this report Počet fotografií označených výstupů přiložených k této zprávě | I57: Committed in the Identification Form Přislíbeno v identifikačním formuláři | K57: =IF('Identification Form'!K90="","",'Identification Form'!K90) -> 20
A58: Handover or opening event with the participation of the Embassy took place Předání nebo slavnostní otevření za účasti velvyslanectví proběhlo | J58: Date Datum
A59: Media or online coverage of the project (name of the medium, date, link) Mediální nebo online výstupy o projektu (název média, datum, odkaz)
A60: 8. Financial Summary in CZK (calculated from the Financial Report) 8. Finanční souhrn v Kč (počítá se z finanční zprávy)
A61: Budget Category Rozpočtová kategorie | F61: Approved (CZK) Schváleno (Kč) | H61: Actually spent (CZK) Skutečně vyčerpáno (Kč) | J61: Difference (CZK) Rozdíl (Kč)
A62: A.1 Material, Goods and Equipment A.1 Materiál, zboží a vybavení | F62: ='Identification Form'!I112 -> 367380.6 | H62: =IF('Financial Report'!$I$65=0,"",'Financial Report'!I20) | J62: =IF(OR('Financial Report'!$I$65=0,H62=""),"",H62-F62)
A63: A.2 Construction and Craft Works A.2 Stavební a řemeslné práce | F63: ='Identification Form'!I120 -> 0 | H63: =IF('Financial Report'!$I$65=0,"",'Financial Report'!I28) | J63: =IF(OR('Financial Report'!$I$65=0,H63=""),"",H63-F63)
A64: A.3 Fees of Lecturers, Trainers and Experts A.3 Odměny lektorů, školitelů a expertů | F64: ='Identification Form'!I128 -> 12495.939 | H64: =IF('Financial Report'!$I$65=0,"",'Financial Report'!I36) | J64: =IF(OR('Financial Report'!$I$65=0,H64=""),"",H64-F64)
A65: A.4 Costs of Training Participants A.4 Náklady účastníků školení | F65: ='Identification Form'!I134 -> 68727.664 | H65: =IF('Financial Report'!$I$65=0,"",'Financial Report'!I42) | J65: =IF(OR('Financial Report'!$I$65=0,H65=""),"",H65-F65)
A66: SUBTOTAL A — PROJECT COSTS MEZISOUČET A — PROJEKTOVÉ NÁKLADY | F66: ='Identification Form'!I135 -> 448604.2 | H66: =IF('Financial Report'!$I$65=0,"",'Financial Report'!I43) | J66: =IF(OR('Financial Report'!$I$65=0,H66=""),"",H66-F66)
A67: B.1 Salaries, Fees and Per Diems of Staff B.1 Mzdy, odměny a diety pracovníků | F67: ='Identification Form'!I143 -> 7497.5633 | H67: =IF('Financial Report'!$I$65=0,"",'Financial Report'!I51) | J67: =IF(OR('Financial Report'!$I$65=0,H67=""),"",H67-F67)
A68: B.2 Travel, Accommodation, Insurance and Vaccination B.2 Cestovné, ubytování, pojištění a očkování | F68: ='Identification Form'!I149 -> 1499.5127 | H68: =IF('Financial Report'!$I$65=0,"",'Financial Report'!I57) | J68: =IF(OR('Financial Report'!$I$65=0,H68=""),"",H68-F68)
A69: B.3 Translations, Bank Charges and Publicity B.3 Překlady, bankovní poplatky a propagace | F69: ='Identification Form'!I155 -> 4373.5786 | H69: =IF('Financial Report'!$I$65=0,"",'Financial Report'!I63) | J69: =IF(OR('Financial Report'!$I$65=0,H69=""),"",H69-F69)
A70: SUBTOTAL B — SUPPORT COSTS MEZISOUČET B — PODPŮRNÉ NÁKLADY | F70: ='Identification Form'!I156 -> 13370.655 | H70: =IF('Financial Report'!$I$65=0,"",'Financial Report'!I64) | J70: =IF(OR('Financial Report'!$I$65=0,H70=""),"",H70-F70)
A71: TOTAL CELKEM | F71: ='Identification Form'!I157 -> 461974.86 | H71: =IF('Financial Report'!$I$65=0,"",'Financial Report'!I65) | J71: =IF(OR('Financial Report'!$I$65=0,H71=""),"",H71-F71)
A72: Support costs (block B) as a share of actual spending — limit 8 % Podpůrné náklady (blok B) jako podíl na skutečném čerpání — limit 8 % | H72: =IF('Financial Report'!G69="","",'Financial Report'!G69) | J72: =IF('Financial Report'!I69="","",'Financial Report'!I69)
A73: 9. Lessons Learned 9. Získané zkušenosti
A74: State what worked, what did not work and what you would do differently. Do not repeat information already given above. Uveďte, co fungovalo, co nefungovalo a co byste udělali jinak. Neopakujte informace uvedené výše.
L75: =LEN(A75)&" / 1000" -> 0 / 1000
A76: 10. Final Clauses 10. Závěrečná ustanovení
A77: Done in (city) Vyhotoveno v (město)
A78: Date Datum
A79: Submitted by (name and position) Předkládá (jméno a funkce)
A80: Telephone Telefon
A81: Email Address E-mailová adresa
A82: Signature Podpis
